MANIFEST.in
setup.py
django_jquery_tablesorter.egg-info/PKG-INFO
django_jquery_tablesorter.egg-info/SOURCES.txt
django_jquery_tablesorter.egg-info/dependency_links.txt
django_jquery_tablesorter.egg-info/requires.txt
django_jquery_tablesorter.egg-info/top_level.txt
jquery_tablesorter/__init__.py
jquery_tablesorter/models.py
jquery_tablesorter/static/css/tablesorter/filter.formatter.css
jquery_tablesorter/static/css/tablesorter/theme.black-ice.css
jquery_tablesorter/static/css/tablesorter/theme.blue.css
jquery_tablesorter/static/css/tablesorter/theme.bootstrap.css
jquery_tablesorter/static/css/tablesorter/theme.dark.css
jquery_tablesorter/static/css/tablesorter/theme.default.css
jquery_tablesorter/static/css/tablesorter/theme.dropbox.css
jquery_tablesorter/static/css/tablesorter/theme.green.css
jquery_tablesorter/static/css/tablesorter/theme.grey.css
jquery_tablesorter/static/css/tablesorter/theme.ice.css
jquery_tablesorter/static/css/tablesorter/theme.jui.css
jquery_tablesorter/static/css/tablesorter/theme.less
jquery_tablesorter/static/css/tablesorter/addons/pager/jquery.tablesorter.pager.css
jquery_tablesorter/static/css/tablesorter/addons/pager/icons/first.png
jquery_tablesorter/static/css/tablesorter/addons/pager/icons/last.png
jquery_tablesorter/static/css/tablesorter/addons/pager/icons/loading.gif
jquery_tablesorter/static/css/tablesorter/addons/pager/icons/next.png
jquery_tablesorter/static/css/tablesorter/addons/pager/icons/prev.png
jquery_tablesorter/static/css/tablesorter/images/black-asc.gif
jquery_tablesorter/static/css/tablesorter/images/black-desc.gif
jquery_tablesorter/static/css/tablesorter/images/black-unsorted.gif
jquery_tablesorter/static/css/tablesorter/images/dropbox-asc-hovered.png
jquery_tablesorter/static/css/tablesorter/images/dropbox-asc.png
jquery_tablesorter/static/css/tablesorter/images/dropbox-desc-hovered.png
jquery_tablesorter/static/css/tablesorter/images/dropbox-desc.png
jquery_tablesorter/static/css/tablesorter/images/green-asc.gif
jquery_tablesorter/static/css/tablesorter/images/green-desc.gif
jquery_tablesorter/static/css/tablesorter/images/green-header.gif
jquery_tablesorter/static/css/tablesorter/images/green-unsorted.gif
