Metadata-Version: 1.1
Name: django-jquery-tablesorter
Version: 2.12.0
Summary: Django package for the tablesorter plugin.
Home-page: https://github.com/mikebryant/django-jquery-tablesorter
Author: Mike Bryant
Author-email: mike@mikebryant.me.uk
License: GPL
Keywords: django,jquery,staticfiles
Platform: any
Classifier: Development Status :: 5 - Production/Stable
Classifier: Environment :: Web Environment
Classifier: Framework :: Django
Classifier: Intended Audience :: Developers
Classifier: Natural Language :: English
Classifier: Operating System :: OS Independent
Classifier: Programming Language :: Python
Classifier: Topic :: Utilities
